chainconsumer/__init__.py
chainconsumer/analysis.py
chainconsumer/base.py
chainconsumer/chain.py
chainconsumer/chainconsumer.py
chainconsumer/color_finder.py
chainconsumer/comparisons.py
chainconsumer/diagnostic.py
chainconsumer/examples.py
chainconsumer/helpers.py
chainconsumer/kde.py
chainconsumer/log.py
chainconsumer/plotter.py
chainconsumer/plotting/__init__.py
chainconsumer/plotting/config.py
chainconsumer/plotting/contours.py
chainconsumer/plotting/truth.py
chainconsumer/plotting/watermark.py
chainconsumer/py.typed
chainconsumer/statistics.py
chainconsumer/truth.py
chainconsumer-1.3.0.dist-info/WHEEL
chainconsumer-1.3.0.dist-info/METADATA
chainconsumer-1.3.0.dist-info/RECORD
