Metadata-Version: 2.4
Name: chainconsumer
Version: 1.3.0
Summary: ChainConsumer: Consume your MCMC chains
Author: Samuel Hinton
Author-email: Samuel Hinton <samuelreay@gmail.com>
License-Expression: MIT
Requires-Dist: numpy>=1.23.0
Requires-Dist: scipy>=1.8.0
Requires-Dist: matplotlib>=3.6.0,<4
Requires-Dist: statsmodels>=0.14.0,<1
Requires-Dist: pandas>=2.1.1,<3
Requires-Dist: pillow>=10.0.1
Requires-Dist: pydantic>=2.2.0,<3
Requires-Python: >=3.10
Project-URL: Documentation, https://samreay.github.io/ChainConsumer
Project-URL: Repository, https://github.com/samreay/ChainConsumer
